{
  "success": "<:success:809460215988355103>",
  "fail": "<:fail:809460215975772252>",
  "info": "<:info:809465929565208616>",
  "fun": "<:fun:809465929477914637>",
  "color": "<:color:809465929867067413>",
  "points": "<:points:809465929968648192>",
  "misc": "<:misc:809465930119249960>",
  "mod": ":beginner:",
  "admin": ":gear:",
  "owner": "<:owner:809460215544152105>",
  "discord_employee": "<:DISCORD_EMPLOYEE:809460214662561813>",
  "discord_partner": "<:DISCORD_PARTNER:809460214910550026>",
  "bughunter_level_1": "<:BUGHUNTER_LEVEL_1:809460214536601630>",
  "bughunter_level_2": "<:BUGHUNTER_LEVEL_2:809460214519562260>",
  "hypesquad_events": "<:HYPESQUAD_EVENTS:809460215576657981>",
  "house_brilliance": "<:HOUSE_BRILLIANCE:809460215376117840>",
  "house_bravery": "<:HOUSE_BRAVERY:809460214503440405>",
  "house_balance": "<:HOUSE_BALANCE:809460214952362054>",
  "early_supporter": "<:EARLY_SUPPORTER:809460214331342880>",
  "verified_bot": "<:VERIFIED_BOT:809460216185356388>",
  "verified_developer": "<:VERIFIED_DEVELOPER:809460216332419132>",
  "online": "<:online:809460215615455262>",
  "idle": "<:idle:809460214893379596>",
  "offline": "<:offline:809460215396827156>",
  "dnd": "<:dnd:809460214905831474>",
  "verify": "<a:verify:747328681420128356>",
  "voice": "<:voice:809460216110120982>",
  "pong": "<:pong:747295268201824307>"
}